AUTHORS
LICENSE.rst
MANIFEST.in
README.rst
REQUIREMENTS
django.patch
setup.py
django_versions.egg-info/PKG-INFO
django_versions.egg-info/SOURCES.txt
django_versions.egg-info/dependency_links.txt
django_versions.egg-info/not-zip-safe
django_versions.egg-info/requires.txt
django_versions.egg-info/top_level.txt
docs/conf.py
docs/index.rst
docs/license.rst
docs/tests.rst
docs/todo.rst
versions/__init__.py
versions/base.py
versions/constants.py
versions/exceptions.py
versions/fields.py
versions/managers.py
versions/middleware.py
versions/models.py
versions/query.py
versions/signals.py
versions/utils.py
versions/backends/__init__.py
versions/backends/base.py
versions/backends/database/__init__.py
versions/backends/database/base.py
versions/backends/database/models.py
versions/backends/hg/__init__.py
versions/backends/hg/base.py
versions/management/__init__.py
versions/management/commands/__init__.py
versions/management/commands/versions_setup.py
versions/tests/__init__.py
versions/tests/models.py
versions/tests/settings.py
versions/tests/tests.py
versions/tests/urls.py